xee/__init__.py
xee/ext.py
xee/ext_integration_test.py
xee/ext_test.py
xee/micro_benchmarks.py
xee/types.py
xee-0.0.22.dist-info/licenses/LICENSE
xee-0.0.22.dist-info/METADATA
xee-0.0.22.dist-info/WHEEL
xee-0.0.22.dist-info/entry_points.txt
xee-0.0.22.dist-info/top_level.txt
xee-0.0.22.dist-info/RECORD
