Metadata-Version: 2.4
Name: xee
Version: 0.0.22
Summary: A Google Earth Engine extension for Xarray.
Author-email: Google LLC <noreply@google.com>
License: Apache-2.0
Project-URL: Homepage, https://github.com/google/xee
Project-URL: Issues, https://github.com/google/Xee/issues
Classifier: Development Status :: 4 - Beta
Classifier: Intended Audience :: Science/Research
Classifier: Intended Audience :: Developers
Classifier: Intended Audience :: Information Technology
Classifier: License :: OSI Approved :: Apache Software License
Classifier: Operating System :: MacOS :: MacOS X
Classifier: Operating System :: Microsoft :: Windows
Classifier: Operating System :: POSIX
Classifier: Programming Language :: Python :: 3.9
Classifier: Programming Language :: Python :: 3.10
Classifier: Programming Language :: Python :: 3.11
Classifier: Programming Language :: Python :: 3.12
Classifier: Programming Language :: Python :: 3.13
Classifier: Topic :: Scientific/Engineering :: Atmospheric Science
Requires-Python: >=3.9
License-File: LICENSE
Requires-Dist: xarray[parallel]
Requires-Dist: earthengine-api>=0.1.374
Requires-Dist: pyproj
Requires-Dist: affine
Provides-Extra: tests
Requires-Dist: absl-py; extra == "tests"
Requires-Dist: pytest; extra == "tests"
Requires-Dist: pyink; extra == "tests"
Requires-Dist: rasterio; extra == "tests"
Requires-Dist: rioxarray; extra == "tests"
Requires-Dist: typing_extensions; extra == "tests"
Provides-Extra: dataflow
Requires-Dist: absl-py; extra == "dataflow"
Requires-Dist: apache-beam[gcp]; extra == "dataflow"
Requires-Dist: gcsfs<=2024.2.0; extra == "dataflow"
Requires-Dist: xarray-beam; extra == "dataflow"
Provides-Extra: examples
Requires-Dist: xee[dataflow]; extra == "examples"
Dynamic: license-file
